tristan/__init__.py
tristan/binning.py
tristan/data.py
tristan/storage.py
tristan/command_line/__init__.py
tristan/command_line/apply_flat_field.py
tristan/command_line/cues.py
tristan/command_line/images/__init__.py
tristan/command_line/images/gated_images_cli.py
tristan/command_line/images/multiple_images_cli.py
tristan/command_line/images/multiple_sequences_cli.py
tristan/command_line/images/pump_probe_cli.py
tristan/command_line/images/single_image_cli.py
tristan/command_line/images/top_level_cli.py
tristan/diagnostics/__init__.py
tristan/diagnostics/check_files.py
tristan/diagnostics/check_valid_events.py
tristan/diagnostics/diagnostics_log.py
tristan/diagnostics/find_trigger_intervals.py
tristan/diagnostics/utils.py
tristan-0.4.2.dist-info/LICENCE
tristan-0.4.2.dist-info/METADATA
tristan-0.4.2.dist-info/WHEEL
tristan-0.4.2.dist-info/entry_points.txt
tristan-0.4.2.dist-info/top_level.txt
tristan-0.4.2.dist-info/RECORD
